gadsqlalchemy/__init__.py
gadsqlalchemy/setup.py
gadsqlalchemy/contextmanagers/__init__.py
gadsqlalchemy/contextmanagers/time.py
gadsqlalchemy/crud/__init__.py
gadsqlalchemy/enums/__init__.py
gadsqlalchemy/enums/engine.py
gadsqlalchemy/exceptions/__init__.py
gadsqlalchemy/patches/__init__.py
gadsqlalchemy/patches/session.py
gadsqlalchemy/tables/__init__.py
gadsqlalchemy/testing/__init__.py
gadsqlalchemy/testing/fixtures.py
gadsqlalchemy/testing/factories/__init__.py
gadsqlalchemy/testing/factories/tables/__init__.py
gadsqlalchemy-0.0.3.dist-info/LICENSE
gadsqlalchemy-0.0.3.dist-info/METADATA
gadsqlalchemy-0.0.3.dist-info/WHEEL
gadsqlalchemy-0.0.3.dist-info/top_level.txt
gadsqlalchemy-0.0.3.dist-info/RECORD
