Metadata-Version: 2.1
Name: gadsqlalchemy
Version: 0.0.3
Summary: Wrapper around SQLAlchemy AsyncSession with built-in query execution profiling and connection context management.
Home-page: https://github.com/AlexDemure/gadsqlalchemy
Author: Alexander Grishchenko
Author-email: alexanderdemure@gmail.com
Classifier: Programming Language :: Python :: 3
Classifier: License :: OSI Approved :: MIT License
Classifier: Operating System :: OS Independent
Requires-Python: >=3.8
License-File: LICENSE
Requires-Dist: factory-boy
Requires-Dist: pytest
Requires-Dist: sqlalchemy
